fastapi_env_banner/__init__.py
fastapi_env_banner/config.py
fastapi_env_banner/middleware.py
fastapi_env_banner/swagger.py
fastapi_env_banner/templates.py
fastapi_env_banner-0.1.0.dist-info/METADATA
fastapi_env_banner-0.1.0.dist-info/WHEEL
fastapi_env_banner-0.1.0.dist-info/licenses/LICENSE
fastapi_env_banner-0.1.0.dist-info/RECORD
