Metadata-Version: 2.4
Name: fastapi-env-banner
Version: 0.1.0
Summary: A lightweight and simple library for adding visual environment banners to FastAPI applications
Project-URL: Homepage, https://github.com/pinnlabs/fastapi-env-banner
Project-URL: Repository, https://github.com/pinnlabs/fastapi-env-banner
Project-URL: Issues, https://github.com/pinnlabs/fastapi-env-banner/issues
Author-email: PinnLabs <hi@pinnlabs.online>
License: MIT
License-File: LICENSE
Keywords: banner,development,environment,fastapi,production,staging
Classifier: Development Status :: 4 - Beta
Classifier: Framework :: FastAPI
Classifier: Intended Audience :: Developers
Classifier: License :: OSI Approved :: MIT License
Classifier: Programming Language :: Python :: 3
Classifier: Programming Language :: Python :: 3.12
Classifier: Topic :: Software Development :: Libraries :: Python Modules
Requires-Python: >=3.12
Requires-Dist: fastapi>=0.119.0
Requires-Dist: starlette>=0.48.0
Provides-Extra: dev
Requires-Dist: httpx>=0.28.1; extra == 'dev'
Requires-Dist: pytest-asyncio>=0.21.0; extra == 'dev'
Requires-Dist: pytest-cov>=4.0.0; extra == 'dev'
Requires-Dist: pytest>=8.4.2; extra == 'dev'
Requires-Dist: uvicorn>=0.18.0; extra == 'dev'
Provides-Extra: docs
Requires-Dist: mkdocs-material>=9.5.0; extra == 'docs'
Requires-Dist: mkdocs>=1.5.0; extra == 'docs'
Requires-Dist: pymdown-extensions>=10.7.0; extra == 'docs'
